lm_simulator/__init__.py
lm_simulator/fake_binaries/dsls/DSLicSrv.out.tmpl
lm_simulator/fake_binaries/dsls/DSLicSrv.py
lm_simulator/fake_binaries/flexlm/lmutil.out.tmpl
lm_simulator/fake_binaries/flexlm/lmutil.py
lm_simulator/fake_binaries/lmx/lmxendutil.out.tmpl
lm_simulator/fake_binaries/lmx/lmxendutil.py
lm_simulator/fake_binaries/lsdyna/lstc_qrun.out.tmpl
lm_simulator/fake_binaries/lsdyna/lstc_qrun.py
lm_simulator/fake_binaries/olicense/olixtool.out.tmpl
lm_simulator/fake_binaries/olicense/olixtool.py
lm_simulator/fake_binaries/rlm/rlmutil.out.tmpl
lm_simulator/fake_binaries/rlm/rlmutil.py
lm_simulator/job_example/application.py
lm_simulator/job_example/batch.sh
license_manager_simulator-4.5.0.dist-info/METADATA
license_manager_simulator-4.5.0.dist-info/WHEEL
license_manager_simulator-4.5.0.dist-info/entry_points.txt
license_manager_simulator-4.5.0.dist-info/licenses/LICENSE
license_manager_simulator-4.5.0.dist-info/RECORD
