Metadata-Version: 2.4
Name: license-manager-simulator
Version: 4.5.0
Summary: The License Manager Simulator is an application that simulates output from 5 license servers for use in the development of applications which interface to the license servers.
License: MIT
License-File: LICENSE
Author: OmniVector Solutions
Author-email: info@omnivector.solutions
Requires-Python: >=3.12,<4.0
Classifier: License :: OSI Approved :: MIT License
Classifier: Programming Language :: Python :: 3
Classifier: Programming Language :: Python :: 3.12
Classifier: Programming Language :: Python :: 3.13
Classifier: Programming Language :: Python :: 3.14
Requires-Dist: Jinja2 (>=3.0.1,<4.0.0)
Requires-Dist: requests (>=2.26.0,<3.0.0)
Project-URL: Documentation, https://omnivector-solutions.github.io/license-manager
Project-URL: Repository, https://github.com/omnivector-solutions/license-manager
